{
    "fluentMethods": true,
    "relationships": [
        {
            "relationshipName": "materia",
            "otherEntityName": "materia",
            "relationshipType": "many-to-many",
            "otherEntityField": "id",
            "ownerSide": true,
            "otherEntityRelationshipName": "aula"
        }
    ],
    "fields": [
        {
            "fieldName": "nombre",
            "fieldType": "String"
        },
        {
            "fieldName": "sigla",
            "fieldType": "String"
        },
        {
            "fieldName": "tipo",
            "fieldType": "String"
        },
        {
            "fieldName": "descripcion",
            "fieldType": "String"
        }
    ],
    "changelogDate": "00000000000200",
    "dto": "no",
    "service": "serviceClass",
    "entityTableName": "aula",
    "jpaMetamodelFiltering": false,
    "pagination": "pager"
}
